<DOMSymbolItem xmlns:xsi="http://www.w3.org/2001/XMLSchema-instance" xmlns="http://ns.adobe.com/xfl/2008/" name="c-pencil-2" itemID="573a3661-00000032" lastModified="1463432811">
  <timeline>
    <DOMTimeline name="c-pencil-2">
      <layers>
        <DOMLayer name="Layer 1" color="#4F80FF" current="true" isSelected="true">
          <frames>
            <DOMFrame index="0" keyMode="9728">
              <elements>
                <DOMBitmapInstance selected="true" libraryItemName="IMG_1709.JPG">
                  <matrix>
                    <Matrix a="0.204254150390625" d="0.204254150390625" tx="-250" ty="-250"/>
                  </matrix>
                </DOMBitmapInstance>
              </elements>
            </DOMFrame>
          </frames>
        </DOMLayer>
      </layers>
    </DOMTimeline>
  </timeline>
</DOMSymbolItem>